{
  "oid": 2034600,
  "uri": "/ladybird/oid/2034600",
  "date": [
    "1961 April"
  ],
  "genre": [
    "Halftones",
    "Magazines (periodicals)",
    "Photographic prints",
    "Photographs",
    "Photomechanical prints"
  ],
  "title": [
    "[Magazine page with various photographs of Leontyne Price]"
  ],
  "extent": [
    "1 p.",
    "34 cm.",
    "b&w illustration"
  ],
  "format": [
    "mixed material"
  ],
  "partOf": "Beinecke Library",
  "rights": [
    "The use of this image may be subject to the copyright law of the United States (Title 17, United States Code) or to site license or other rights management terms and conditions. The person using the image is liable for any infringement."
  ],
  "source": "ladybird",
  "abstract": [
    "Reproduced photographs accompanying article about Leontyne Price's visit to hometown of Laurel, Miss."
  ],
  "children": [

  ],
  "language": [
    "English"
  ],
  "callNumber": "JWJ A +Eb74",
  "orbisBibId": "752400",
  "recordType": "oid",
  "repository": "Beinecke Library",
  "contributor": [
    "Price, Leontyne"
  ],
  "sourceTitle": "Ebony magazine",
  "subjectName": [
    "Price, Leontyne"
  ],
  "collectionId": 1,
  "resourceType": "Books, Journals & Pamphlets",
  "dependentUris": [
    "/ladybird/oid/2034600"
  ],
  "sourceCreated": "Chicago : Johnson Pub. Co",
  "dateStructured": [
    "1961-04-00T00:00:00Z"
  ],
  "itemPermission": "Public",
  "subjectGeographic": [
    "Laurel (Miss.)"
  ],
  "contributorDisplay": [
    "Price, Leontyne"
  ],
  "extentOfDigitization": [
    "Partial work digitized."
  ]
}